ragstack_langchain/__init__.py
ragstack_langchain/colbert/__init__.py
ragstack_langchain/colbert/colbert_retriever.py
ragstack_langchain/colbert/colbert_vector_store.py
ragstack_langchain/colbert/embedding.py
ragstack_langchain/py.typed
ragstack_ai_langchain-1.4.0.dist-info/METADATA
ragstack_ai_langchain-1.4.0.dist-info/WHEEL
ragstack_ai_langchain-1.4.0.dist-info/RECORD
